odoo/addons/partner_contact_address_default/README.rst
odoo/addons/partner_contact_address_default/__init__.py
odoo/addons/partner_contact_address_default/__manifest__.py
odoo/addons/partner_contact_address_default/i18n/es.po
odoo/addons/partner_contact_address_default/i18n/it.po
odoo/addons/partner_contact_address_default/i18n/partner_contact_address_default.pot
odoo/addons/partner_contact_address_default/i18n/pt.po
odoo/addons/partner_contact_address_default/models/__init__.py
odoo/addons/partner_contact_address_default/models/res_config_settings.py
odoo/addons/partner_contact_address_default/models/res_partner.py
odoo/addons/partner_contact_address_default/readme/CONTRIBUTORS.rst
odoo/addons/partner_contact_address_default/readme/DESCRIPTION.rst
odoo/addons/partner_contact_address_default/readme/USAGE.rst
odoo/addons/partner_contact_address_default/security/res_groups_security.xml
odoo/addons/partner_contact_address_default/static/description/icon.png
odoo/addons/partner_contact_address_default/static/description/index.html
odoo/addons/partner_contact_address_default/tests/__init__.py
odoo/addons/partner_contact_address_default/tests/test_partner_contact_address_default.py
odoo/addons/partner_contact_address_default/views/res_config_settings_views.xml
odoo/addons/partner_contact_address_default/views/res_partner_views.xml
odoo12_addon_partner_contact_address_default-12.0.1.3.0.dist-info/METADATA
odoo12_addon_partner_contact_address_default-12.0.1.3.0.dist-info/WHEEL
odoo12_addon_partner_contact_address_default-12.0.1.3.0.dist-info/top_level.txt
odoo12_addon_partner_contact_address_default-12.0.1.3.0.dist-info/RECORD
