Metadata-Version: 2.1
Name: odoo12-addon-partner-contact-address-default
Version: 12.0.1.3.0
Summary: Set a default delivery and invoice address for contacts
Home-page: https://github.com/OCA/partner-contact
Author: Tecnativa, Odoo Community Association (OCA)
Author-email: support@odoo-community.org
License: AGPL-3
Platform: UNKNOWN
Classifier: Programming Language :: Python
Classifier: Framework :: Odoo
Classifier: Framework :: Odoo :: 12.0
Classifier: License :: OSI Approved :: GNU Affero General Public License v3
Classifier: Development Status :: 4 - Beta
Requires-Python: >=3.5
Requires-Dist: odoo (<12.1dev,>=12.0a)
